[
    { "text": "CPU nima vazifani bajaradi?", "options": ["Hisoblash va boshqaruv", "Ma'lumot saqlash", "Rasm chiqarish", "Ovoz chiqarish"], "correct": 0 },
    { "text": "RAM nima?", "options": ["Tezkor xotira", "Doimiy xotira", "Tashqi xotira", "Optik disk"], "correct": 0 },
    { "text": "Operatsion tizimga misol keltiring", "options": ["Windows, Linux, macOS", "Word, Excel", "Chrome, Firefox", "CPU, RAM"], "correct": 0 },
    { "text": "HDD va SSD farqi?", "options": ["SSD tezroq, HDD sekinroq", "HDD tezroq, SSD sekinroq", "Hech qanday farq yo'q", "SSD arzonroq"], "correct": 0 },
    { "text": "Fayl kengaytmasi .exe nimani anglatadi?", "options": ["Bajariladigan fayl", "Matn fayli", "Rasm fayli", "Ovoz fayli"], "correct": 0 },
    { "text": "URL nima?", "options": ["Veb-manzil", "Elektron pochta", "Fayl yoli", "Server nomi"], "correct": 0 },
    { "text": "Browser (brauzer) nima?", "options": ["Veb-sahifalarni ko'rish dasturi", "Operatsion tizim", "Ofis dasturi", "Antivirus"], "correct": 0 },
    { "text": "Email qanday maqsadda ishlatiladi?", "options": ["Elektron xat yuborish", "Veb-sahifa yaratish", "Rasm tahrirlash", "Ovoz yozish"], "correct": 0 },
    { "text": "Cloud storage nima?", "options": ["Bulutli ma'lumotlar ombori", "Fizik disk", "Operatsion tizim", "Antivirus"], "correct": 0 },
    { "text": "VPN nima uchun ishlatiladi?", "options": ["Maxfiy va xavfsiz ulanish", "Internet tezligini oshirish", "Antivirus sifatida", "Operatsion tizim sifatida"], "correct": 0 },
    { "text": "Firewall nima vazifani bajaradi?", "options": ["Tarmoq xavfsizligini ta'minlash", "Ma'lumot saqlash", "Rasm chiqarish", "Ovoz chiqarish"], "correct": 0 },
    { "text": "Phishing nima?", "options": ["Soxta veb-saytlar orqali ma'lumot o'g'irlash", "Virus tarqatish", "Kompyuterni tezlatish", "Fayllarni siqish"], "correct": 0 },
    { "text": "Antivirus dasturi nima?", "options": ["Zararli dasturlardan himoya qiladi", "Operatsion tizim", "Ofis dasturi", "Browser"], "correct": 0 },
    { "text": "Cloud computing nima?", "options": ["Internet orqali xizmatlar taqdim etish", "Fizik server", "Operatsion tizim", "Ma'lumotlar bazasi"], "correct": 0 },
    { "text": "IP address nima?", "options": ["Tarmoqdagi qurilma manzili", "Veb-sayt nomi", "Elektron pochta manzili", "Fayl yoli"], "correct": 0 },
    { "text": "Wi-Fi nima?", "options": ["Simsiz tarmoq texnologiyasi", "Simli tarmoq", "Operatsion tizim", "Antivirus"], "correct": 0 },
    { "text": "Bluetooth nima uchun ishlatiladi?", "options": ["Qisqa masofaga ma'lumot uzatish", "Internetga ulanish", "Ovoz chiqarish", "Rasm chiqarish"], "correct": 0 },
    { "text": "USB nima?", "options": ["Universal ketma-ket shina", "Operatsion tizim", "Antivirus", "Browser"], "correct": 0 },
    { "text": "BIOS nima?", "options": ["Asosiy kirish-chiqish tizimi", "Operatsion tizim", "Antivirus", "Ofis dasturi"], "correct": 0 },
    { "text": "Driver nima?", "options": ["Qurilmalarni boshqaruvchi dastur", "Operatsion tizim", "Antivirus", "Browser"], "correct": 0 },
    { "text": "Open source nima?", "options": ["Ochiq kodli dastur", "Yopiq kodli dastur", "Pullik dastur", "Bepul dastur"], "correct": 0 },
    { "text": "Google Docs nima?", "options": ["Bulutli ofis dasturi", "Operatsion tizim", "Antivirus", "Browser"], "correct": 0 },
    { "text": "Zoom asosan nima uchun ishlatiladi?", "options": ["Video konferensiya", "Rasm tahrirlash", "Ovoz yozish", "Matn yozish"], "correct": 0 },
    { "text": "Telegram nima?", "options": ["Messenger dastur", "Operatsion tizim", "Antivirus", "Ofis dasturi"], "correct": 0 },
    { "text": "Instagram nima?", "options": ["Ijtimoiy tarmoq", "Operatsion tizim", "Antivirus", "Ofis dasturi"], "correct": 0 }
]