[
    { "text": "She ___ to school every day.", "options": ["go", "goes", "going", "went"], "correct": 1 },
    { "text": "They ___ playing football now.", "options": ["is", "am", "are", "be"], "correct": 2 },
    { "text": "I ___ to the cinema yesterday.", "options": ["go", "goes", "went", "gone"], "correct": 2 },
    { "text": "He has ___ finished his homework.", "options": ["yet", "already", "still", "ever"], "correct": 1 },
    { "text": "If I ___ you, I would study harder.", "options": ["am", "was", "were", "is"], "correct": 2 },
    { "text": "She ___ English for five years.", "options": ["has been learning", "have been learning", "is learning", "was learning"], "correct": 0 },
    { "text": "This is the book ___ I bought yesterday.", "options": ["who", "which", "whose", "whom"], "correct": 1 },
    { "text": "Let's go to the park, ___?", "options": ["shall we", "will we", "can we", "do we"], "correct": 0 },
    { "text": "Neither John nor his friends ___ present.", "options": ["is", "am", "are", "be"], "correct": 2 },
    { "text": "She advised me ___ late.", "options": ["not be", "not to be", "to not be", "don't be"], "correct": 1 },
    { "text": "The movie was ___ boring than I expected.", "options": ["more", "most", "very", "much"], "correct": 0 },
    { "text": "I wish I ___ taller.", "options": ["am", "was", "were", "is"], "correct": 2 },
    { "text": "She ___ her keys. She can't find them anywhere.", "options": ["lost", "has lost", "loses", "is losing"], "correct": 1 },
    { "text": "The car ___ I bought is red.", "options": ["who", "which", "whose", "whom"], "correct": 1 },
    { "text": "He used to ___ smoking, but now he doesn't.", "options": ["smoke", "smoking", "smoked", "smokes"], "correct": 0 },
    { "text": "She is ___ honest person.", "options": ["a", "an", "the", "none"], "correct": 1 },
    { "text": "We ___ each other for ages.", "options": ["know", "have known", "knew", "are knowing"], "correct": 1 },
    { "text": "She is ___ than her sister.", "options": ["intelligent", "more intelligent", "most intelligent", "intelligenter"], "correct": 1 },
    { "text": "He told me that he ___ come.", "options": ["will", "would", "can", "may"], "correct": 1 },
    { "text": "I don't have ___ money.", "options": ["some", "any", "no", "many"], "correct": 1 },
    { "text": "She is looking forward to ___ you.", "options": ["see", "seeing", "saw", "seen"], "correct": 1 },
    { "text": "By the time we arrived, the party ___ already started.", "options": ["has", "have", "had", "was"], "correct": 2 },
    { "text": "He is ___ young to drive.", "options": ["so", "too", "very", "enough"], "correct": 1 },
    { "text": "She ___ be at home; the lights are on.", "options": ["must", "can't", "might", "should"], "correct": 0 },
    { "text": "I'd rather ___ at home tonight.", "options": ["to stay", "stay", "staying", "stayed"], "correct": 1 }
]